tutorfrontpage/__about__.py
tutorfrontpage/__init__.py
tutorfrontpage/plugin.py
tutorfrontpage/patches/caddyfile
tutorfrontpage/patches/local-docker-compose-jobs-services
tutorfrontpage/patches/local-docker-compose-nginx-volumes
tutorfrontpage/patches/local-docker-compose-services
tutorfrontpage/patches/nginx-extra
tutorfrontpage/patches/openedx-lms-production-settings
tutorfrontpage/patches/proxy-nginx
tutorfrontpage/templates/frontpage/apps/settings/tutor.py
tutorfrontpage/templates/frontpage/build/frontpage/Dockerfile
tutorfrontpage/templates/frontpage/hooks/frontpage/init
tutorfrontpage/templates/frontpage/hooks/lms/init
tutorfrontpage/templates/frontpage/hooks/mysql/init
tutor_contrib_frontpage-0.1.0.dist-info/METADATA
tutor_contrib_frontpage-0.1.0.dist-info/WHEEL
tutor_contrib_frontpage-0.1.0.dist-info/entry_points.txt
tutor_contrib_frontpage-0.1.0.dist-info/top_level.txt
tutor_contrib_frontpage-0.1.0.dist-info/RECORD
